MANIFEST.in
README.txt
setup.py
docs/COPYRIGHT.txt
docs/HISTORY.txt
docs/LICENSE.txt
src/cromlech/__init__.py
src/cromlech.wsgistate.egg-info/PKG-INFO
src/cromlech.wsgistate.egg-info/SOURCES.txt
src/cromlech.wsgistate.egg-info/dependency_links.txt
src/cromlech.wsgistate.egg-info/entry_points.txt
src/cromlech.wsgistate.egg-info/namespace_packages.txt
src/cromlech.wsgistate.egg-info/not-zip-safe
src/cromlech.wsgistate.egg-info/requires.txt
src/cromlech.wsgistate.egg-info/top_level.txt
src/cromlech/wsgistate/__init__.py
src/cromlech/wsgistate/controlled.py
src/cromlech/wsgistate/middleware.py
src/cromlech/wsgistate/test_session.txt
src/cromlech/wsgistate/timeout.py