Metadata-Version: 1.1
Name: cromlech.wsgistate
Version: 0.3b2
Summary: Session handling for cromlech using wsgistate
Home-page: http://gitweb.dolmen-project.org/
Author: The Dolmen team
Author-email: dolmen@list.dolmen-project.org
License: ZPL
Keywords: Cromlech Wsgistate Session
Platform: UNKNOWN
Classifier: Programming Language :: Python
